iblog/__init__.py
iblog/__main__.py
iblog/issue.py
iblog/api_server/__init__.py
iblog/api_server/api.py
iblog/mq_server/__init__.py
iblog/schedule_server/__init__.py
iblog-0.0.6.dist-info/LICENSE
iblog-0.0.6.dist-info/METADATA
iblog-0.0.6.dist-info/WHEEL
iblog-0.0.6.dist-info/entry_points.txt
iblog-0.0.6.dist-info/top_level.txt
iblog-0.0.6.dist-info/zip-safe
iblog-0.0.6.dist-info/RECORD
