Metadata-Version: 2.1
Name: iblog
Version: 0.0.6
Summary: Issue blog.
Home-page: https://github.com/openjw/blog
Author: kingreatwill
Author-email: 350840291@qq.com
License: UNKNOWN
Keywords: issue,blog
Platform: UNKNOWN
Requires-Dist: flask (>=1.1.2)
Requires-Dist: kafka-python (>=2.0.1)
Requires-Dist: pika (>=1.1.0)
Requires-Dist: apscheduler (>=3.6.3)
Requires-Dist: PyGithub (>=1.53)
Requires-Dist: pygitee (>=1.0.0)
